dbus2mqtt/__init__.py
dbus2mqtt/__main__.py
dbus2mqtt/event_broker.py
dbus2mqtt/main.py
dbus2mqtt/config/__init__.py
dbus2mqtt/config/jsonarparse.py
dbus2mqtt/dbus/dbus_client.py
dbus2mqtt/dbus/dbus_types.py
dbus2mqtt/dbus/dbus_util.py
dbus2mqtt/dbus/introspection_patches/mpris_playerctl.py
dbus2mqtt/dbus/introspection_patches/mpris_vlc.py
dbus2mqtt/flow/__init__.py
dbus2mqtt/flow/flow_processor.py
dbus2mqtt/flow/actions/context_set.py
dbus2mqtt/flow/actions/log_action.py
dbus2mqtt/flow/actions/mqtt_publish.py
dbus2mqtt/mqtt/mqtt_client.py
dbus2mqtt/template/__init__.py
dbus2mqtt/template/dbus_template_functions.py
dbus2mqtt/template/templating.py
dbus2mqtt-0.6.0.dist-info/METADATA
dbus2mqtt-0.6.0.dist-info/WHEEL
dbus2mqtt-0.6.0.dist-info/entry_points.txt
dbus2mqtt-0.6.0.dist-info/licenses/LICENSE
dbus2mqtt-0.6.0.dist-info/RECORD
