Metadata-Version: 2.4
Name: dbus2mqtt
Version: 0.6.0
Summary: General purpose DBus to MQTT bridge - expose signals, methods and properties over MQTT - featuring jinja based templating, payload enrichment and MPRIS / BlueZ / Home Assistant ready examples 
Project-URL: Documentation, https://jwnmulder.github.io/dbus2mqtt
Project-URL: Source, https://github.com/jwnmulder/dbus2mqtt
Project-URL: Issues, https://github.com/jwnmulder/dbus2mqtt/issues
License-Expression: MIT
License-File: LICENSE
Keywords: bluez,bridge,dbus,home-assistant,jinja2,mpris,mqtt,python
Classifier: Development Status :: 5 - Production/Stable
Classifier: Intended Audience :: Developers
Classifier: License :: OSI Approved :: MIT License
Classifier: Operating System :: POSIX :: Linux
Classifier: Programming Language :: Python :: 3
Classifier: Programming Language :: Python :: 3.10
Classifier: Programming Language :: Python :: 3.11
Classifier: Programming Language :: Python :: 3.12
Classifier: Programming Language :: Python :: 3.13
Classifier: Programming Language :: Python :: 3.14
Classifier: Topic :: Home Automation
Requires-Python: >=3.10
Requires-Dist: apscheduler==3.11.2
Requires-Dist: colorlog>=6.9.0
Requires-Dist: dbus-fast==3.1.2
Requires-Dist: janus>=2.0.0
Requires-Dist: jinja2-ansible-filters==1.3.2
Requires-Dist: jinja2==3.1.6
Requires-Dist: jsonargparse==4.45.0
Requires-Dist: paho-mqtt==2.1.0
Requires-Dist: python-dotenv>=1.1.0
Requires-Dist: pyyaml>=6.0.2
